Metadata-Version: 2.1
Name: kikyo-sz
Version: 0.1.3
Summary: kikyo-sz package
Author: jadbin
Author-email: jadbin.com@hotmail.com
License: MIT
Classifier: License :: OSI Approved :: MIT License
Classifier: Intended Audience :: Developers
Classifier: Programming Language :: Python
Classifier: Programming Language :: Python :: 3
Classifier: Topic :: Software Development :: Libraries :: Python Modules
Requires-Python: >=3.6
License-File: LICENSE
